RKP/RKP.py
RKP/__init__.py
RKP-0.1.0.data/scripts/RKP.py
RKP-0.1.0.data/scripts/create_kmers.sh
RKP-0.1.0.data/scripts/heatmap.R
RKP-0.1.0.data/scripts/map_kmers.sh
RKP-0.1.0.dist-info/LICENSE
RKP-0.1.0.dist-info/METADATA
RKP-0.1.0.dist-info/WHEEL
RKP-0.1.0.dist-info/top_level.txt
RKP-0.1.0.dist-info/RECORD
