Metadata-Version: 2.1
Name: RKP
Version: 0.1.0
Summary: Relative K-mer Project
Home-page: https://gitlab.com/microbial_genomics/relative-kmer-project
Author: Lennard Epping, Felix Hartkopf
Author-email: EppingL@rki.de, HartkopfF@rki.de
License: UNKNOWN
Platform: UNKNOWN
Classifier: Programming Language :: Python :: 3
Classifier: License :: OSI Approved :: GNU General Public License v3 (GPLv3)
Classifier: Operating System :: POSIX :: Linux
Requires-Python: >=3.6
Requires-Dist: numpy (==1.17.3)
Requires-Dist: matplotlib (==3.1.2)
Requires-Dist: pandas (==0.25.3)
Requires-Dist: biopython (==1.76)
Requires-Dist: argparse (==1.4.0)
Requires-Dist: tqdm (==4.41.1)
